DynamicMachine-1.0.4.data/scripts/configure_machine.py
DynamicMachine-1.0.4.data/scripts/create_machine.py
DynamicMachine-1.0.4.data/scripts/delete_machines.py
DynamicMachine-1.0.4.data/scripts/list_keys.py
DynamicMachine-1.0.4.data/scripts/list_locations.py
DynamicMachine-1.0.4.data/scripts/list_sizes.py
DynamicMachine-1.0.4.data/scripts/list_targets.py
dynamic_machine/__init__.py
dynamic_machine/cli_commands.py
dynamic_machine/cli_commands_test.py
dynamic_machine/cli_process_json.py
dynamic_machine/cli_process_json_test.py
dynamic_machine/cli_ssh.py
dynamic_machine/cli_ssh_test.py
dynamic_machine/inventory.py
dynamic_machine/machine.py
providers/__init__.py
DynamicMachine-1.0.4.dist-info/LICENSE.txt
DynamicMachine-1.0.4.dist-info/METADATA
DynamicMachine-1.0.4.dist-info/WHEEL
DynamicMachine-1.0.4.dist-info/top_level.txt
DynamicMachine-1.0.4.dist-info/RECORD
